LICENSE
MANIFEST.in
README.md
setup.py
test.py
salesforce_oauth_request/__init__.py
salesforce_oauth_request/utils.py
salesforce_oauth_request.egg-info/PKG-INFO
salesforce_oauth_request.egg-info/SOURCES.txt
salesforce_oauth_request.egg-info/dependency_links.txt
salesforce_oauth_request.egg-info/not-zip-safe
salesforce_oauth_request.egg-info/requires.txt
salesforce_oauth_request.egg-info/top_level.txt