Metadata-Version: 1.1
Name: salesforce-oauth-request
Version: 1.0.2
Summary: Util package to drive Salesforce Oauth Web flow for testing.
Home-page: https://github.com/heroku/salesforce-oauth-request
Author: Scott Persinger
Author-email: scottp@heroku.com
License: Copyright (c) 2013 Scott Persinger
